__init__.py
item.py
pdf2txt.py
settings.py
setup.py
zot.py
zot.egg-info/PKG-INFO
zot.egg-info/SOURCES.txt
zot.egg-info/dependency_links.txt
zot.egg-info/entry_points.txt
zot.egg-info/requires.txt
zot.egg-info/top_level.txt