Metadata-Version: 1.0
Name: zot
Version: 0.1.3
Summary: zotero command-line interface
Home-page: https://github.com/hourchallenge/zot
Author: Ben Morris
Author-email: ben@bendmorris.com
License: UNKNOWN
Platform: UNKNOWN
